[
  {
    "id": "0701f15e-3c38-4afa-9321-689722f6b96b",
    "creatorHex": "458a4bef0ed7a9ec102cb6ce800fdd973d18dc19e856e0876d42bc167dc9a371",
    "creatorNpub": "npub1458a4bef0ed7a9ec",
    "creatorDisplayName": "ALICE4",
    "type": "BUY",
    "amountSats": 300000,
    "currency": "USD",
    "price": 45000.0,
    "useMarketPrice": true,
    "premiumPercent": 0.0,
    "minTradeSats": 0,
    "maxTradeSats": 300000,
    "paymentMethod": "BANK_TRANSFER",
    "location": "india",
    "locationDetail": "",
    "description": "Looking to buy BTC. Quick and reliable payment.",
    "terms": "",
    "escrowTimeHours": 24,
    "status": "ACTIVE",
    "createdAt": "2026-01-08T16:47:37.113713476",
    "expiresAt": "2026-01-15T16:47:37.115578962",
    "publishedAt": "2026-01-08T16:47:37.115566578"
  },
  {
    "id": "56aa9fba-0f46-4e5d-b32c-0f2b12fbdb8a",
    "creatorHex": "3edba9b422261e09c288185f49680e2e6001f46b4ca35ba7be8bf371094cea9b",
    "creatorNpub": "npub13edba9b422261e09",
    "creatorDisplayName": "ALICE",
    "type": "BUY",
    "amountSats": 100000000,
    "currency": "USD",
    "price": 45000.0,
    "useMarketPrice": true,
    "premiumPercent": 0.0,
    "minTradeSats": 0,
    "maxTradeSats": 100000000,
    "paymentMethod": "BANK_TRANSFER",
    "location": "BADAJOZ",
    "locationDetail": "",
    "description": "Looking to buy BTC. Quick and reliable payment.",
    "terms": "",
    "escrowTimeHours": 24,
    "status": "ACTIVE",
    "createdAt": "2026-01-08T16:47:10.323609092",
    "expiresAt": "2026-01-04T19:55:37.763002956",
    "publishedAt": "2025-12-28T19:55:37.762989641"
  },
  {
    "id": "5a791e77-cf8f-4ce3-a3d0-3f29e6b69908",
    "nostrEventId": "aedea35cb329fed01afd333e45df2dfc2e50d209ad5dd8e7158307d7f2b87e84",
    "creatorHex": "e7ef52e47ba58876a5662a2cebfe373b28bacbb314eb2be756073beed15dee3d",
    "creatorNpub": "npub1e7ef52e47ba58876",
    "creatorDisplayName": "ALICE",
    "type": "BUY",
    "amountSats": 1200000000,
    "currency": "USD",
    "price": 45000.0,
    "useMarketPrice": true,
    "premiumPercent": 0.0,
    "minTradeSats": 0,
    "maxTradeSats": 1200000000,
    "paymentMethod": "BANK_TRANSFER",
    "location": "PONTEVEDRA",
    "locationDetail": "",
    "description": "Looking to buy BTC. Quick and reliable payment.",
    "terms": "",
    "escrowTimeHours": 24,
    "status": "ACTIVE",
    "createdAt": "2026-01-08T16:47:10.323922370",
    "expiresAt": "2026-01-04T21:08:00.746885416",
    "publishedAt": "2025-12-28T21:08:00.746873984"
  },
  {
    "id": "7e2bf5cd-87a8-48b8-8174-26eacdaa146f",
    "creatorHex": "d8bfb4c4f872edc30b16d988f15a6be4e1557cc19541d6cda83b0534dc50f838",
    "creatorNpub": "npub1d8bfb4c4f872edc3",
    "creatorDisplayName": "ALICE",
    "type": "BUY",
    "amountSats": 800000000,
    "currency": "USD",
    "price": 45000.0,
    "useMarketPrice": true,
    "premiumPercent": 0.0,
    "minTradeSats": 0,
    "maxTradeSats": 800000000,
    "paymentMethod": "BANK_TRANSFER",
    "location": "LUGO",
    "locationDetail": "",
    "description": "Looking to buy BTC. Quick and reliable payment.",
    "terms": "",
    "escrowTimeHours": 24,
    "status": "ACTIVE",
    "createdAt": "2026-01-08T16:47:10.324015116",
    "expiresAt": "2026-01-04T20:36:18.804147345",
    "publishedAt": "2025-12-28T20:36:18.804137437"
  },
  {
    "id": "453ee154-711d-475a-988c-146aa2691956",
    "nostrEventId": "44f3b2034d1845c8b1d5d27a52630645c7fc6320779489031b6042714da3f46b",
    "creatorHex": "d8bfb4c4f872edc30b16d988f15a6be4e1557cc19541d6cda83b0534dc50f838",
    "creatorNpub": "npub1d8bfb4c4f872edc3",
    "creatorDisplayName": "ALICE",
    "type": "BUY",
    "amountSats": 100000000,
    "currency": "USD",
    "price": 45000.0,
    "useMarketPrice": true,
    "premiumPercent": 0.0,
    "minTradeSats": 0,
    "maxTradeSats": 100000000,
    "paymentMethod": "BANK_TRANSFER",
    "location": "SPAIN",
    "locationDetail": "",
    "description": "Looking to buy BTC. Quick and reliable payment.",
    "terms": "",
    "escrowTimeHours": 24,
    "status": "ACTIVE",
    "createdAt": "2026-01-08T16:47:10.324117432",
    "expiresAt": "2026-01-04T20:32:06.247424249",
    "publishedAt": "2025-12-28T20:32:06.247412076"
  },
  {
    "id": "251fa060-c0bd-49da-b19f-294ef97567f6",
    "nostrEventId": "2e7d8d62c1c4f1c8f4c1c405727ab28686a96686b4ddd75d3d71b1a231786a7a",
    "creatorHex": "458a4bef0ed7a9ec102cb6ce800fdd973d18dc19e856e0876d42bc167dc9a371",
    "creatorNpub": "npub1458a4bef0ed7a9ec",
    "creatorDisplayName": "ALICE4",
    "type": "BUY",
    "amountSats": 1000000,
    "currency": "USD",
    "price": 45000.0,
    "useMarketPrice": true,
    "premiumPercent": 0.0,
    "minTradeSats": 0,
    "maxTradeSats": 1000000,
    "paymentMethod": "BANK_TRANSFER",
    "location": "denmark",
    "locationDetail": "gffgfdsghfdfsghfd",
    "description": "Looking to buy BTC. Quick and reliable payment.",
    "terms": "",
    "escrowTimeHours": 24,
    "status": "ACTIVE",
    "createdAt": "2026-01-08T16:47:10.324209407",
    "expiresAt": "2026-01-15T16:26:51.272719105",
    "publishedAt": "2026-01-08T16:26:51.272710138"
  }
]